pyfc4/__init__.py
pyfc4/models.py
pyfc4/plugins/__init__.py
pyfc4/plugins/pcdm/__init__.py
pyfc4/plugins/pcdm/examples.py
pyfc4/plugins/pcdm/models.py
pyfc4-0.7.dist-info/LICENSE.md
pyfc4-0.7.dist-info/METADATA
pyfc4-0.7.dist-info/WHEEL
pyfc4-0.7.dist-info/top_level.txt
pyfc4-0.7.dist-info/RECORD
